prometheus_pandas/__init__.py
prometheus_pandas/query.py
prometheus_pandas/util.py
prometheus_pandas/ipython/__init__.py
prometheus_pandas/ipython/magic.py
prometheus_pandas-0.3.3.dist-info/LICENSE
prometheus_pandas-0.3.3.dist-info/METADATA
prometheus_pandas-0.3.3.dist-info/WHEEL
prometheus_pandas-0.3.3.dist-info/top_level.txt
prometheus_pandas-0.3.3.dist-info/RECORD
