Metadata-Version: 2.1
Name: prometheus-pandas
Version: 0.3.3
Summary: Pandas integration for Prometheus
Home-page: https://github.com/dcoles/prometheus-pandas
Classifier: Programming Language :: Python :: 3
Classifier: License :: OSI Approved :: MIT License
Classifier: Operating System :: OS Independent
Requires-Python: >=3.6
License-File: LICENSE
Requires-Dist: numpy
Requires-Dist: pandas
